<?xml version = '1.0' encoding = 'UTF-8'?>
<Relation class="oracle.dbtools.crest.model.design.logical.Relation" name="pode_possuir" directorySegmentName="seg_0" id="631E7EEE-9B95-2551-A557-73E3CE85E796">
<createdBy>Dnx</createdBy>
<createdTime>2022-10-05 13:12:06 UTC</createdTime>
<ownerDesignName>challenge_bd</ownerDesignName>
<importedID>F4D10F39-51D6-C190-A05F-28E187FE4BBF</importedID>
<engineerTo>
<item key="DFF2A775-1FD6-D7FA-DE38-E862D46C69A0" value="true"/>
<item key="0F449CEB-2274-5C1B-B080-1FA872AFE873" value="true"/>
<item key="ACF90852-88E7-2F36-4283-FF04B473F388" value="true"/>
</engineerTo>
<sourcePk>F5A46E55-A4CF-DFCD-EE16-94BB3FC645FA</sourcePk>
<identifying>false</identifying>
<optionalSource>true</optionalSource>
<optionalTarget>false</optionalTarget>
<sourceCardinality>1</sourceCardinality>
<sourceEntity>50BD0F92-1DED-5222-AE09-43EB3FA7B02B</sourceEntity>
<targetCardinalityString>*</targetCardinalityString>
<targetEntity>8B68F1B2-BF1B-42EC-6A4F-83B107D9EE8D</targetEntity>
<transferable>true</transferable>
<deleteRule>NO ACTION</deleteRule>
</Relation>